{
  "noiseKey": {
    "private": {
      "type": "Buffer",
      "data": "wHCRHKoWXIbpZsLEqdKWT5RlSSs2zF9isJ6Vy/Binkw="
    },
    "public": {
      "type": "Buffer",
      "data": "W8y01av5ODFwkNyBFRMl086clwkkchknNlUzrQ7pnmI="
    }
  },
  "pairingEphemeralKeyPair": {
    "private": {
      "type": "Buffer",
      "data": "8HMP/2ffKY2vgQM5xX9cZKmdGBM1qQZnxg2ZgB6elHw="
    },
    "public": {
      "type": "Buffer",
      "data": "AwTRspHSy+VKaNvu18oZFBH06WjAyVKNHkiWGjJaFTk="
    }
  },
  "signedIdentityKey": {
    "private": {
      "type": "Buffer",
      "data": "aBw0SfG2INcsQqhWtEj89EQaEjskNk7PnnTuBm7yslw="
    },
    "public": {
      "type": "Buffer",
      "data": "ZEJj7sY0aqaY9qtHq75Tr0oqGBWXpKjB6vKlgRF8fS0="
    }
  },
  "signedPreKey": {
    "keyPair": {
      "private": {
        "type": "Buffer",
        "data": "GPhvalF58Bp1p/Ub7BfvA9yTXexRL2JdmxPFrObmi3g="
      },
      "public": {
        "type": "Buffer",
        "data": "s1vNCMLseOqT6HwQVebq6/jUFcrzkcIXGhV+oNblH2k="
      }
    },
    "signature": {
      "type": "Buffer",
      "data": "8dgW5rkMaEGc55ZVcvoEqnZ1nh8M8bg20OTPFfulKFd5cmTf2DLeKuQtgJj52yzaLqNcSowicwlS/MG+wLD4jQ=="
    },
    "keyId": 1
  },
  "registrationId": 64,
  "advSecretKey": "VssGpYPFx1LVNYzNQB+MP0pPBO7WcDcCEp91lBn9KIQ=",
  "processedHistoryMessages": [
    {
      "key": {
        "remoteJid": "94773644070@s.whatsapp.net",
        "fromMe": true,
        "id": "04186E8175E605E33EFBF75392A7C607"
      },
      "messageTimestamp": 1755193932
    },
    {
      "key": {
        "remoteJid": "94773644070@s.whatsapp.net",
        "fromMe": true,
        "id": "B3BEBEFC5B6B6B91B4AA3491D801EB01"
      },
      "messageTimestamp": 1755193934
    },
    {
      "key": {
        "remoteJid": "94773644070@s.whatsapp.net",
        "fromMe": true,
        "id": "9B1D347305B667600FAF86BF204D99C4"
      },
      "messageTimestamp": 1755193951
    }
  ],
  "nextPreKeyId": 35,
  "firstUnuploadedPreKeyId": 35,
  "accountSyncCounter": 1,
  "accountSettings": {
    "unarchiveChats": false
  },
  "registered": true,
  "pairingCode": "ESBSVZBF",
  "me": {
    "id": "94773644070:50@s.whatsapp.net",
    "lid": "273224529121318:50@lid",
    "name": "Hansitha•®"
  },
  "account": {
    "details": "CN3Q7PMDELvE+MQGGAIgACgA",
    "accountSignatureKey": "z70PCbAU4pjSDOqreMEzhAw8MHMLzJBTsZUpCk5LdDU=",
    "accountSignature": "71MELdCWyRg5UkXQr4uUseg1reY8Pfst2dzWTr+K2qRJvnFwvDocAOjn6OdzmVLMAK0ru1vRj3pHfBacHwrEAQ==",
    "deviceSignature": "RohJm3WtfYxbdBGlk89GJdhTCS5VDgrAFJTLU4fjkj2UdEdNd/cJk0jticvKgEYPpYkC4mtXrnZkSAqdoNnsgw=="
  },
  "signalIdentities": [
    {
      "identifier": {
        "name": "94773644070:50@s.whatsapp.net",
        "deviceId": 0
      },
      "identifierKey": {
        "type": "Buffer",
        "data": "Bc+9DwmwFOKY0gzqq3jBM4QMPDBzC8yQU7GVKQpOS3Q1"
      }
    }
  ],
  "platform": "android",
  "routingInfo": {
    "type": "Buffer",
    "data": "CA0IBQ=="
  },
  "lastAccountSyncTimestamp": 1755193976,
  "lastPropHash": "2V77qU",
  "myAppStateKeyId": "AAAAAFBN"
}