{
  "noiseKey": {
    "private": {
      "type": "Buffer",
      "data": "KPpi6jQvEu2W5jwdbdpohVFX6nDSCylelkv5ki3YTHo="
    },
    "public": {
      "type": "Buffer",
      "data": "LW3v/O/YoIDRf2Zmvmlbm53jY+1i1sAZJ5Gi/+wHDTw="
    }
  },
  "pairingEphemeralKeyPair": {
    "private": {
      "type": "Buffer",
      "data": "EJED5AzCm8FtFNHwTSQxbCeTCpnw2LpltufRdk2E6UY="
    },
    "public": {
      "type": "Buffer",
      "data": "mfWYkb+kqI9kia0+5WUTmFKC9f6AFpzS/1Y2B3WPKVA="
    }
  },
  "signedIdentityKey": {
    "private": {
      "type": "Buffer",
      "data": "sKkjZLd/pfBb4Shh7xJaGxuyQF3KcQ0TZ5MZJZhph0I="
    },
    "public": {
      "type": "Buffer",
      "data": "vxyLe+f8SJlEFvCcFXakYUiRtc6aE9YaJKnAIHBP+xk="
    }
  },
  "signedPreKey": {
    "keyPair": {
      "private": {
        "type": "Buffer",
        "data": "AF9fQdPYp8oUVaP758nWPttG/5Us7xleAwZIUIWenXA="
      },
      "public": {
        "type": "Buffer",
        "data": "xWaeN5kKrspB/oTnOEClQUBJeRZigMq2swhJZic9TkE="
      }
    },
    "signature": {
      "type": "Buffer",
      "data": "1mMLsZzaTaSQTTppYtXgUl+5m/KY7ueeiIjD1yxIfZsKHVqKTarKuiWKSXQfLrStOcaekQkuD5Scxlx6HnFPCQ=="
    },
    "keyId": 1
  },
  "registrationId": 177,
  "advSecretKey": "kgmJ02eE8FsEHq/hvmwFG/LxVp0mjyngngUi+WqN4wA=",
  "processedHistoryMessages": [
    {
      "key": {
        "remoteJid": "447432603349@s.whatsapp.net",
        "fromMe": true,
        "id": "685CCDDBAAA3CE2363984E9FA7DF9E23"
      },
      "messageTimestamp": 1755257610
    },
    {
      "key": {
        "remoteJid": "447432603349@s.whatsapp.net",
        "fromMe": true,
        "id": "0F701E0C7C7BB52EC9BFC587ACBE050E"
      },
      "messageTimestamp": 1755257610
    }
  ],
  "nextPreKeyId": 32,
  "firstUnuploadedPreKeyId": 32,
  "accountSyncCounter": 1,
  "accountSettings": {
    "unarchiveChats": false
  },
  "registered": true,
  "pairingCode": "RABPALQP",
  "me": {
    "id": "447432603349:3@s.whatsapp.net",
    "lid": "78804697542796:3@lid",
    "name": "༒𝐋𝐎𝐑𝐃 𝐌𝐀𝐋𝐂𝐎𝐋𝐌༒"
  },
  "account": {
    "details": "CInJxrUEEPW1/MQGGAMgACgA",
    "accountSignatureKey": "xo+zm1gCl2wYDneReRCQETikFpBEGOZyce2tnmHGUh8=",
    "accountSignature": "SHgzVD9LOnshby2wK/jQ5Vgy9qYgTtfqqkWwCzvYxC1KXLZGziIKUKTushmfgiG4YpTubka5Joypwa1YxOgIAA==",
    "deviceSignature": "Fh2Fu0nJJAwBuVH8Rboumed104rGS1rb/FORUTA7PELwW76bGlP3j208TK1ndX6l/m3NRgOh9O018uIPM8mcCw=="
  },
  "signalIdentities": [
    {
      "identifier": {
        "name": "447432603349:3@s.whatsapp.net",
        "deviceId": 0
      },
      "identifierKey": {
        "type": "Buffer",
        "data": "BcaPs5tYApdsGA53kXkQkBE4pBaQRBjmcnHtrZ5hxlIf"
      }
    }
  ],
  "platform": "android",
  "routingInfo": {
    "type": "Buffer",
    "data": "CAgIBQ=="
  },
  "lastAccountSyncTimestamp": 1755257603,
  "lastPropHash": "3R9Z39",
  "myAppStateKeyId": "AAAAAMA+"
}